swaml/__init__.py
swaml/main.py
swaml-0.1.1.dist-info/entry_points.txt
swaml-0.1.1.dist-info/LICENSE
swaml-0.1.1.dist-info/WHEEL
swaml-0.1.1.dist-info/METADATA
swaml-0.1.1.dist-info/RECORD
